<?xml version="1.0" encoding="UTF-8"?><record_update table="sc_cat_item_catalog">
    <sc_cat_item_catalog action="INSERT_OR_UPDATE">
        <sc_cat_item display_value="full decommission of unity lun">09c246e8db5310104c815c7a4896198d</sc_cat_item>
        <sc_catalog display_value="Service Catalog">e0d08b13c3330100c8b837659bba8fb4</sc_catalog>
        <sys_class_name>sc_cat_item_catalog</sys_class_name>
        <sys_created_by>admin</sys_created_by>
        <sys_created_on>2020-09-22 14:12:15</sys_created_on>
        <sys_id>44321b1fdb1350104c815c7a489619e7</sys_id>
        <sys_mod_count>0</sys_mod_count>
        <sys_name>Service Catalog.full decommission of unity lun</sys_name>
        <sys_package display_value="unity-brocade-mvp" source="x_440435_unity_bro">b7efaa0cdb1f10104c815c7a48961925</sys_package>
        <sys_policy/>
        <sys_scope display_value="unity-brocade-mvp">b7efaa0cdb1f10104c815c7a48961925</sys_scope>
        <sys_update_name>sc_cat_item_catalog_44321b1fdb1350104c815c7a489619e7</sys_update_name>
        <sys_updated_by>admin</sys_updated_by>
        <sys_updated_on>2020-09-22 14:12:15</sys_updated_on>
    </sc_cat_item_catalog>
</record_update>
